universal_constraints/__init__.py
universal_constraints/apps.py
universal_constraints/auto_discovery.py
universal_constraints/constraint_converter.py
universal_constraints/settings.py
universal_constraints/validators.py
universal_constraints/management/commands/discover_constraints.py
django_universal_constraints-1.1.1.dist-info/METADATA
django_universal_constraints-1.1.1.dist-info/WHEEL
django_universal_constraints-1.1.1.dist-info/licenses/LICENSE
django_universal_constraints-1.1.1.dist-info/RECORD
