Metadata-Version: 2.4
Name: django-universal-constraints
Version: 1.1.1
Summary: Universal conditional/unique constraint support for Django - makes unique constraints work with ANY database backend
Project-URL: Homepage, https://github.com/j2k-studio/django-universal-constraints
Project-URL: Repository, https://github.com/j2k-studio/django-universal-constraints
Project-URL: Documentation, https://github.com/j2k-studio/django-universal-constraints
Project-URL: Bug Tracker, https://github.com/j2k-studio/django-universal-constraints/issues
Author-email: J2K Studio <dev@j2k.studio>
License-File: LICENSE
Keywords: backend,compatibility,constraints,database,django,unique,validation
Classifier: Development Status :: 5 - Production/Stable
Classifier: Environment :: Web Environment
Classifier: Framework :: Django
Classifier: Framework :: Django :: 4.2
Classifier: Framework :: Django :: 5.0
Classifier: Framework :: Django :: 5.1
Classifier: Framework :: Django :: 5.2
Classifier: Intended Audience :: Developers
Classifier: License :: OSI Approved :: MIT License
Classifier: Operating System :: OS Independent
Classifier: Programming Language :: Python
Classifier: Programming Language :: Python :: 3
Classifier: Programming Language :: Python :: 3.8
Classifier: Programming Language :: Python :: 3.9
Classifier: Programming Language :: Python :: 3.10
Classifier: Programming Language :: Python :: 3.11
Classifier: Programming Language :: Python :: 3.12
Classifier: Topic :: Database
Classifier: Topic :: Internet :: WWW/HTTP
Classifier: Topic :: Software Development :: Libraries :: Python Modules
Requires-Python: >=3.8
Requires-Dist: django>=4.2
